{
  "symbol": "XRP/USD",
  "name": "Ripple vs US Dollar",
  "nameCn": "瑞波币/美元",
  "timestamp": "2026-03-10T12:55:34.083Z",
  "price": {
    "close": "1.38734",
    "high": "1.39193",
    "low": "1.38269",
    "open": "1.39103",
    "change": "-0.24",
    "datetime": "2026-03-10 12:00:00"
  },
  "indicators": {
    "rsi": 54.59785,
    "macd": 0.010225411,
    "macd_signal": 0.0093335015,
    "sma20": 1.38057
  },
  "analysis": {
    "zh": {
      "title": "瑞波币/美元技术分析：短期盘整偏强",
      "content": "当前XRP/USD价格位于1.38734附近，接近日内高点1.39193，显示市场短期存在轻微上行动能。价格略高于20日简单移动均线(SMA20=1.38057)，表明中短期多头趋势仍然存在，但涨幅有限，市场呈现盘整特征。  \n\nMACD指标为0.0102，虽未提供信号线，但正值显示多头动能占优，买卖力量略倾向上行。不过，涨幅不足以突破近期阻力位1.392，暗示上攻动力有限，需要关注突破确认。支撑方面，1.383为短期关键支撑位，若跌破则可能触发回调，投资者需警惕止损。  \n\n交易策略上，短线可考虑高抛低吸策略，逢低靠近1.383附近适合短线买入，目标价位靠近1.392或日内高点。若价格稳步突破1.392且伴随成交量放大，可视为趋势延续信号，适合短线追涨，但需设定严格止损以防快速回落。  \n\n总的来看，XRP/USD短期维持盘整偏强格局，多空力量相对平衡，投资者可保持观望并结合支撑阻力进行灵活操作，谨慎把握进出场时机，避免盲目追高或过度恐慌抛售。"
    },
    "en": {
      "title": "Ripple vs US Dollar Technical Analysis",
      "content": "XRP/USD is showing a mild consolidation phase around the $1.387 level after a slight 24-hour decline of 0.24%. Price action has remained contained between the intraday high of $1.39193 and low of $1.38269, suggesting limited volatility. The short-term trend appears neutral to slightly bullish, supported by the 20-period SMA at $1.38057, which is acting as a dynamic support. Traders should monitor whether the price can hold above this moving average, as a breakdown could signal a deeper correction.\n\nMomentum indicators provide a mixed picture. The MACD is slightly positive at 0.0102, indicating a potential for upward movement, though the absence of a signal line makes it harder to confirm strength. The lack of a current RSI reading limits clarity on overbought or oversold conditions. Despite this, the proximity to the SMA suggests that buyers remain present around key support zones, keeping short-term upside potential alive while cautioning against aggressive long positions.\n\nKey support is established near $1.380, reinforced by the SMA, with a secondary support around $1.375 if the initial level fails. Resistance is near $1.392, the intraday high, with an extended target around $1.400, which could act as a psychological barrier. Price behavior around these levels will be critical in defining the next directional move. A strong break above resistance may signal continuation of bullish momentum, while a failure to sustain above SMA support could open the path to consolidation or minor declines.\n\nFor traders, a cautious approach is recommended. Short-term buyers may consider entering near $1.380-$1.382 with tight stop-losses below $1.375, targeting the $1.392-$1.400 range. Sellers could look for a rebound at resistance levels for potential short positions, ensuring risk management is in place given the narrow price range. Overall, XRP/USD appears poised for gradual movement, with technical signals favoring a balanced view rather than a decisive trend at this stage."
    }
  }
}