{
  "symbol": "DOGE/USD",
  "name": "Dogecoin vs US Dollar",
  "nameCn": "狗狗币/美元",
  "timestamp": "2026-03-11T11:24:47.782Z",
  "price": {
    "close": "0.09216",
    "high": "0.09242",
    "low": "0.09207",
    "open": "0.09223",
    "change": "-0.05",
    "datetime": "2026-03-11 11:00:00"
  },
  "indicators": {
    "rsi": 42.80917,
    "macd": -0.00054538074,
    "macd_signal": -0.00023807368,
    "sma20": 0.0938695
  },
  "analysis": {
    "zh": {
      "title": "狗狗币/美元技术分析：短期偏弱整理，承压下行风险存在",
      "content": "当前狗狗币价格在0.09216附近小幅波动，日内涨跌幅有限，显示市场短期缺乏明确方向。从价格与20日简单移动均线(SMA20)比较来看，现价低于SMA20(0.09387)，表明短期承压，偏向弱势整理格局，可能在关键支撑位附近震荡。  \n\nMACD指标显示负值且低于零轴，短期空头动能占优，但由于信号线数据缺失，需要关注后续走势的确认信号。RSI数据暂不可用，但结合价格与均线偏离，可推测多空力量处于均衡偏弱状态，市场仍需等待新资金入场或重大消息刺激。  \n\n支撑位关注0.0920附近，该位置为近期低点，若跌破可能引发进一步回调；阻力位在0.0938-0.0940区域，与SMA20及前高重合，是短期空头回补压力区。交易上可考虑低多高空策略，谨慎控制仓位，避免追高或频繁短线操作。  \n\n综合来看，狗狗币短期仍偏弱震荡，投资者应重点关注支撑位能否守住，同时留意短线动能指标回暖信号，确认反弹后再逐步布局。止损设置在0.0918以下可降低下行风险，谨慎操作为宜。"
    },
    "en": {
      "title": "Dogecoin vs US Dollar Technical Analysis",
      "content": "Dogecoin (DOGE) against the US Dollar (USD) has shown a slight negative price movement of -0.05% in the past 24 hours, with the price fluctuating between a high of $0.09242 and a low of $0.09207. The current price of $0.09216 reflects a minor correction in what seems to be a broader sideways market structure. Given the proximity of the price to the 20-period simple moving average (SMA) of $0.09387, Dogecoin is likely experiencing consolidation near this level. If the market continues to range, DOGE/USD may struggle to break through key resistance or support in the short term.\n\nThe absence of the Relative Strength Index (RSI) and the lack of a defined signal line in the MACD prevent a clear reading of overbought or oversold conditions, as well as potential trend reversals. However, the MACD value of -0.000545 indicates a slight bearish momentum, suggesting a weaker market sentiment. This subtle bearish tone implies that DOGE/USD may be more susceptible to further downside pressure if it fails to hold above its immediate support level. Traders should keep an eye on any MACD crossovers or the appearance of an RSI reading to confirm potential shifts in momentum.\n\nSupport for Dogecoin in the near term appears to be at $0.09207, where the price has previously tested the lower range. If this level holds, a mild rebound to the upside toward the SMA could be seen, with the next potential resistance around $0.09387. A break below $0.09207 may trigger a further decline toward the $0.091 support region, signaling further bearish potential. A sustained move above $0.09387 could suggest an upside breakout, though this would require significant bullish volume to maintain momentum.\n\nIn light of the current market conditions, the most prudent strategy for traders might involve range-bound trading, targeting short-term moves between $0.09207 and $0.09387. However, caution should be exercised, as the lack of strong bullish signals and the slightly bearish MACD reading suggest the possibility of further consolidation or slight downside. Traders should remain flexible, adjusting their positions as the indicators evolve."
    }
  }
}