{
  "symbol": "ADA/USD",
  "name": "Cardano vs US Dollar",
  "nameCn": "艾达币/美元",
  "timestamp": "2026-03-16T02:05:10.997Z",
  "price": {
    "close": "0.271557",
    "high": "0.271557",
    "low": "0.271156",
    "open": "0.271505",
    "change": "0.03",
    "datetime": "2026-03-16 02:00:00"
  },
  "indicators": {
    "rsi": 69.89676,
    "macd": 0.001866019,
    "macd_signal": 0.001082578,
    "sma20": 0.2661865
  },
  "analysis": {
    "zh": {
      "title": "艾达币/美元技术分析：[震荡整理，短期暂无明显趋势]",
      "content": "当前艾达币/美元（ADA/USD）价格处于0.271557附近，全天波动幅度较小，显示市场仍处于整理阶段。虽然价格未出现明显突破，但在当前区间内，价格保持相对平稳，显示出一定的横盘整理特征。短期内，市场似乎缺乏强烈的买卖动能。\n\n从技术指标来看，当前没有RSI和MACD信号提供明确的买入或卖出信号，市场情绪保持中性。SMA(20)线支撑在0.2662附近，这可能成为短期的支撑位。如果价格跌破这一水平，则可能会出现进一步的下行压力。MACD值为0.001866，显示出微弱的正值，表明价格有一定的上涨动力，但整体没有强势趋势。\n\n从支撑位来看，0.2662是当前价格的关键支撑，如果价格跌破该区域，可能会向下寻找更低的支撑区域。上方阻力位在0.2750附近，一旦突破此阻力位，可能会带来较强的上涨动力。总体来看，艾达币处于震荡整理区间，建议投资者保持观望，待突破关键支撑或阻力位后再考虑入场。"
    },
    "en": {
      "title": "Cardano vs US Dollar Technical Analysis",
      "content": "Cardano (ADA) is currently showing a mild bullish bias as it hovers around $0.2716, slightly above the 20-day simple moving average of $0.2662. This positioning suggests that short-term momentum is leaning toward accumulation, despite the negligible 24-hour price change of 0.03%. The narrow high/low range ($0.271557–$0.271156) indicates low volatility and market indecision, a period where buyers and sellers are waiting for a clear catalyst. Traders should watch for a decisive breakout above $0.275 to confirm further upward momentum.  \n\nThe MACD reading of 0.00187 points to a modest bullish momentum, although the absence of a signal line limits the reliability of a crossover-based assessment. In the current context, the small positive MACD implies that upward pressure is present but not strong. Without a clear RSI, it is difficult to determine overbought or oversold conditions, so market participants should rely on price action and volume trends to gauge potential continuation or reversal. Monitoring sudden shifts in volume could provide early warning for trend acceleration.  \n\nSupport for ADA/USD is evident near $0.266, aligned with the 20-day SMA, while immediate resistance sits around $0.275. A breach below the SMA could signal a short-term retracement, targeting $0.262 as the next support level. On the upside, sustaining above $0.275 could open a path toward $0.28–$0.282, where sellers may re-enter. These levels define a tight trading corridor, suggesting that scalping and short-term swing strategies may be preferable in this low-volatility environment.  \n\nFor trading strategies, conservative participants may consider entering long positions on dips toward $0.266–$0.267 with stop-losses slightly below $0.262. More aggressive traders could look for breakout trades above $0.275, aiming for the $0.28 zone while managing risk with tight trailing stops. Given the current sideways consolidation, patience is key, and confirmation from either higher volume or price breaking key support/resistance levels should guide position sizing and timing.  \n\nWord count: 276"
    }
  }
}