{
  "symbol": "ADA/USD",
  "name": "Cardano vs US Dollar",
  "nameCn": "艾达币/美元",
  "timestamp": "2026-05-27T22:56:52.295Z",
  "price": {
    "close": "0.237147",
    "high": "0.238658",
    "low": "0.236255",
    "open": "0.237539",
    "change": "-0.16",
    "datetime": "2026-05-27 22:00:00"
  },
  "indicators": {
    "rsi": 38.21651,
    "macd": -0.00067938206,
    "macd_signal": -0.00052550424,
    "sma20": 0.2397347
  },
  "analysis": {
    "zh": {
      "title": "艾达币/美元技术分析：短线偏弱震荡整理",
      "content": "当前ADA/USD维持窄幅震荡，价格运行于0.237附近，日内波动有限。由于价格持续处在20日均线下方，短线趋势仍偏空，市场情绪相对谨慎，多头暂未形成有效反攻结构。\n\n从技术指标观察，MACD维持在零轴下方且呈负值，说明空头动能仍有延续，但柱体缩短显示下跌力度开始放缓。RSI数据暂缺，不过结合价格结构来看，市场仍处于弱势整理阶段。\n\n关键支撑位关注0.2362一线，若失守可能进一步测试0.2340区域；上方阻力则位于0.2397至0.2410区间，尤其20日均线附近存在较强抛压，短期突破难度较高。\n\n交易策略方面，激进交易者可关注支撑位附近的短线反弹机会，但需严格设置止损。稳健投资者建议等待价格重新站稳0.240上方后，再考虑顺势跟进，以降低震荡行情中的交易风险。"
    },
    "en": {
      "title": "Cardano vs US Dollar Technical Analysis",
      "content": "Cardano’s price action against the US Dollar is showing signs of mild consolidation around the $0.237 level. The latest intraday trading range between $0.236 and $0.238 suggests that the market is testing short-term support without a decisive trend breakout. While the 24-hour change of -0.16% is minimal, it indicates slight bearish pressure. The overall trend appears neutral to mildly bearish in the very short term, as the price remains under the 20-period simple moving average at $0.2397, signaling resistance above.\n\nLooking at momentum indicators, the MACD shows a negative value of -0.000679, hinting at prevailing bearish sentiment, although the absence of a signal line reading limits confirmation. Traders should watch for a crossover or divergence in the MACD for clearer directional cues. The RSI is not available, making it difficult to gauge overbought or oversold conditions, but the price hovering just below the SMA(20) suggests sellers currently maintain control. A break above the SMA could indicate renewed bullish momentum.\n\nKey support and resistance levels for ADA/USD are crucial for trade planning. Immediate support lies around $0.2363, which has held during recent dips. On the upside, resistance sits near $0.2397, the SMA level, and a secondary resistance is at the recent high of $0.2387. These levels could serve as pivot points for short-term traders. Any decisive break below support may trigger further downward movement toward $0.234, while a sustained break above resistance could open room for a rally toward $0.242.\n\nTrading strategies should remain cautious under the current sideways conditions. Short-term traders might consider range-bound strategies, buying near support and selling near resistance, while maintaining tight stop-losses to manage risk. Momentum traders may wait for MACD confirmation or a price break above the SMA to enter long positions. Conservative investors may prefer to monitor broader market signals before committing, given the current lack of strong trend confirmation and muted volatility."
    }
  }
}