{
  "symbol": "XRP/USD",
  "name": "Ripple vs US Dollar",
  "nameCn": "瑞波币/美元",
  "timestamp": "2026-04-03T15:30:33.434Z",
  "price": {
    "close": "1.32052",
    "high": "1.32321",
    "low": "1.31879",
    "open": "1.31881",
    "change": "0.12",
    "datetime": "2026-04-03 15:00:00"
  },
  "indicators": {
    "rsi": 53.45876,
    "macd": 0.00052267448,
    "macd_signal": -0.00036236617,
    "sma20": 1.31738
  },
  "analysis": {
    "zh": {
      "title": "瑞波币/美元技术分析：短线震荡偏多",
      "content": "当前XRP/USD价格徘徊在1.320附近，结合20日均线1.317可见，价格略高于SMA，显示短期仍具支撑力。24小时波动幅度有限，市场整体处于震荡整理阶段，多空力量相对均衡。若价格稳住在均线之上，短线多头仍有延续可能。  \n\nMACD指标显示0.00052267448，虽信号线缺失，但指标为正，暗示多头动能尚存。然而缺乏RSI数据限制了超买超卖判断，需要关注后续动能变化。若MACD持续上行并形成金叉，将进一步确认上涨趋势，否则可能面临回调压力。  \n\n支撑位方面，可关注1.317附近的SMA及近期低点1.318，若跌破可能触发短线空头情绪。阻力位在近期高点1.323及心理整数位1.33，短线突破将有助于上行确认。价格在区间震荡中，可利用支撑与阻力进行波段操作。  \n\n交易上建议短线多单可在支撑附近尝试入场，止损设置低于1.317，目标关注1.323至1.33阻力区间。若价格跌破关键支撑，则应谨慎减仓或择机做空，以控制风险。整体来看，短线偏多，但需警惕区间震荡带来的波动。"
    },
    "en": {
      "title": "Ripple vs US Dollar Technical Analysis",
      "content": "> search(\"You are a professional cryptocurrency analyst. Provide technical analysis for Ripple vs US Dollar (XRP/USD).\\n\\nCurrent Market Data:\\n- Latest Price: 1.32052\\n- 24h Change: 0.12%\\n- High/Low: 1.32321 / 1.31879\\n- RSI(14): N/A\\n- MACD: 0.00052267448, Signal: N/A\\n- SMA(20): 1.31738\\n\\nRequirements:\\n1. Write 3-4 paragraphs, 60-80 words each, total 250-300 words\\n2. Include: trend analysis, indicator interpretation, support/resistance levels, trading suggestions\\n3. Use professional but accessible language\\n4. No labels, no meta-commentary\\n5. Start immediately with the content (no title needed)\\n\\nBegin:\")\n\nThe XRP/USD pair currently hovers slightly above the 20‑period simple moving average at **1.31738**, suggesting a modest bullish bias in the short term. Price action within the **1.318–1.323** range shows consolidation after recent sideways movement. This near‑term plateau, combined with a tiny 24‑hour gain, hints that sellers and buyers are in a temporary equilibrium. If the pair holds above the SMA(20), the slight upward tilt could gradually attract momentum traders looking for sustained strength.\n\nOn indicators, the **positive MACD reading (~0.0005227)** albeit without a clear signal line reference, suggests underlying buying pressure. Without the full MACD signal data or RSI, we must cautiously interpret this as early accumulation rather than decisive trend confirmation. The lack of a defined RSI reading leaves overbought/oversold conditions ambiguous, heightening the importance of watching momentum shifts around key price zones. Traders should treat the MACD’s positive bias as tentative until corroborated by other oscillators or volume expansion.\n\nImmediate **support lies near 1.318–1.315**, which aligns with the SMA and recent swing lows. A deeper retracement toward **1.310** could attract buyers seeking value entries. On the upside, **resistance near 1.330** and then **1.340–1.350** emerges from recent highs and congestion bands. Breaking above 1.330 with convincing volume would open the door toward re‑testing 1.350, while a clear failure below 1.315 risks a deeper pullback into previous congestion around 1.300.\n\nFor trading suggestions, short‑term traders might consider **scaling into longs** above 1.322 with tight stops below 1.315, aiming for targets near 1.335–1.345. More conservative participants may await a **break and retest above 1.330** before committing, reducing the risk of range‑bound whipsaws. Conversely, bearish setups could emerge if price decisively closes below 1.315, prompting short exposure toward 1.300 with disciplined risk management."
    }
  }
}