{
  "symbol": "AVAX/USD",
  "name": "Avalanche vs US Dollar",
  "nameCn": "雪崩币/美元",
  "timestamp": "2025-12-16T05:48:00.032Z",
  "price": {
    "close": "12.2421",
    "high": "12.2421",
    "low": "12.1829",
    "open": "12.2038",
    "change": "0.28",
    "datetime": "2025-12-16 05:00:00"
  },
  "indicators": {
    "rsi": 28.98379,
    "macd": -0.21271743,
    "macd_signal": -0.20448148,
    "sma20": 12.5291
  },
  "analysis": {
    "zh": {
      "title": "雪崩币/美元技术分析：[当前市场微弱反弹]",
      "content": "当前雪崩币（AVAX）对美元的价格在12.2421附近波动，显示出市场在经历小幅反弹。虽然24小时变化仅为0.28%，但这种微弱反弹可能反映出市场参与者对该币种的信心尚未完全恢复。短期内，趋势仍显疲软，投资者需谨慎。\n\n从技术指标来看，MACD值为-0.2127，显示出卖压依然存在，且RSI指标暂缺乏，无法提供过度买入或卖出的信号。然而，20日简单移动平均线（SMA）在12.5291处，表明价格仍低于该均线，进一步强化了市场的看跌情绪。\n\n支撑位方面，12.1829是当前的重要支撑线，若价格跌破此位，可能会引发更多的抛售。反之，若价格能有效突破12.5291的阻力位，可能会带来新的买入机会。因此，投资者需密切关注这两个关键水平。\n\n在交易建议上，建议短期内保持观望，待市场趋势进一步明朗后再做决策。若价格出现反弹并突破阻力位，可以考虑适度入场；若跌破支撑位，则应及时止损，保护资金安全。"
    },
    "en": {
      "title": "Avalanche vs US Dollar Technical Analysis",
      "content": "The current price of Avalanche (AVAX) against the US Dollar stands at 12.2421, indicating a slight upward movement of 0.28% over the past 24 hours. This modest gain suggests a consolidation phase after a period of volatility. The recent high of 12.2421 shows that buyers are attempting to regain control, but the low of 12.1829 indicates that selling pressure remains present. Traders should closely monitor these levels for potential breakout or breakdown signals.\n\nIn terms of technical indicators, the absence of an RSI reading complicates momentum analysis, but the MACD value of -0.2127 suggests bearish sentiment may still be in play. A negative MACD indicates that recent price action is underperforming relative to its historical trend. Meanwhile, the 20-day Simple Moving Average (SMA) at 12.5291 serves as a key resistance level. A price movement above this SMA could signal a bullish reversal, while a failure to do so could reinforce bearish sentiment.\n\nSupport levels appear to be forming around the recent low of 12.1829. A break below this level could open the door to further declines, potentially testing lower supports. Conversely, if buyers manage to hold above this support while pushing towards the SMA, it may suggest a constructive buildup for a rally. Traders should establish their positions accordingly, considering stop-loss orders just below support to mitigate risks.\n\nFor short-term trading strategies, a cautious approach is advisable. Traders might consider entering long positions if AVAX breaks above the 20-day SMA with strong volume, signaling increased buying interest. On the other hand, if the price dips below the 12.1829 support, short positions could be warranted, with targets set at lower support levels to capitalize on potential downward momentum. Keeping an eye on market news and sentiment will also be crucial for informed decision-making."
    }
  }
}