{
  "symbol": "DOGE/USD",
  "name": "Dogecoin vs US Dollar",
  "nameCn": "狗狗币/美元",
  "timestamp": "2026-01-03T01:20:23.960Z",
  "price": {
    "close": "0.14214",
    "high": "0.14242",
    "low": "0.1416",
    "open": "0.14185",
    "change": "0.19",
    "datetime": "2026-01-03 01:00:00"
  },
  "indicators": {
    "rsi": 73.43636,
    "macd": 0.0042647256,
    "macd_signal": 0.00392127,
    "sma20": 0.1358785
  },
  "analysis": {
    "zh": {
      "title": "狗狗币/美元技术分析：[震荡整理，等待突破信号]",
      "content": "当前DOGE/USD的价格为0.14214，整体市场表现平稳，24小时内变化仅为0.19%。从高点0.14242和低点0.1416来看，价格在一个窄幅区间内震荡整理，表明市场缺乏明确的方向性，短期内可能继续保持震荡格局。\n\n在技术指标方面，尽管RSI尚不可用，但MACD值为0.0042647256，表明多头力量相对较弱，市场仍需关注后续趋势变化。同时，20日简单移动平均线(SMA)为0.13587850，显示出价格在这一线附近存在一定的支撑位，若跌破此位，则可能引发进一步的回调。\n\n支撑位方面，0.1416为关键支撑，若下破该水平，可能会测试更低的支撑区间。反之，0.14242为短期阻力位，突破此位将为多头提供更多信心，推动价格进一步上涨。因此，交易者应密切关注这两个关键水平的突破情况。\n\n在操作建议方面，建议交易者在当前区间内采取区间交易策略，关注支撑和阻力的表现。若价格有效突破0.14242，可以考虑小幅买入，若跌破0.1416则应谨慎评估风险，适时止损以保护资金安全。"
    },
    "en": {
      "title": "Dogecoin vs US Dollar Technical Analysis",
      "content": "The current price of Dogecoin (DOGE) against the US Dollar (USD) stands at 0.14214, reflecting a slight increase of 0.19% over the past 24 hours. This modest upward movement may suggest a potential bullish trend in the short term, especially given that the price has managed to stay within a narrow range between the recent high of 0.14242 and a low of 0.1416. Observing this consolidation phase can provide traders with insight into market sentiment and potential breakout opportunities.\n\nIn terms of technical indicators, the MACD at 0.0042647256 indicates a bullish momentum, although the absence of a signal line complicates further analysis. The lack of RSI data makes it challenging to gauge overbought or oversold conditions at this moment. However, the simple moving average (SMA) of 20 periods at 0.13587850 suggests that the price is currently above this level, reinforcing a bullish sentiment. A close above this SMA could signal a continuation of upward momentum, while a drop below may indicate a reversal.\n\nKey support levels for DOGE can be identified around the recent low of 0.1416, which could serve as a crucial point for buyers to step in. Conversely, resistance is evident at the recent high of 0.14242, where selling pressure may emerge. A breakout above this resistance could pave the way for higher targets, while failure to maintain above support could lead to a retest of lower levels. \n\nTraders might consider entering long positions if the price successfully breaches the resistance level with strong volume, aiming for targets above 0.1450. Conversely, if the price falls below the support level, a cautious approach would be advisable, possibly looking to short or exit positions to mitigate losses. Overall, monitoring these indicators and levels closely will be key to navigating the current DOGE/USD landscape effectively."
    }
  }
}