{
  "symbol": "ADA/USD",
  "name": "Cardano vs US Dollar",
  "nameCn": "艾达币/美元",
  "timestamp": "2026-01-14T20:21:14.452Z",
  "price": {
    "close": "0.415944",
    "high": "0.417692",
    "low": "0.414323",
    "open": "0.414959",
    "change": "0.24",
    "datetime": "2026-01-14 20:00:00"
  },
  "indicators": {
    "rsi": 51.91543,
    "macd": 0.0019370412,
    "macd_signal": 0.0033391252,
    "sma20": 0.41924525
  },
  "analysis": {
    "zh": {
      "title": "艾达币/美元技术分析：[当前趋势偏弱]",
      "content": "当前，艾达币（ADA）在0.415944美元附近交易，24小时变化仅为0.24%。从价格走势来看，ADA正处于一个相对窄幅的区间内，未能突破0.417692美元的高点，显示出市场的犹豫和缺乏方向感。短期内，若价格持续维持在当前区间内，可能会导致进一步的整理。\n\n在技术指标方面，虽然RSI尚不可用，但MACD显示出微弱的正值，表明短期内可能存在一些买盘支持。然而，SMA（20）位于0.41924525，表明短期平均价格略高于当前价格，可能形成一定的阻力。综合来看，短期内市场情绪较为谨慎。\n\n支撑位方面，0.414323美元作为近期低点，可能会为价格提供支撑。如果价格跌破此水平，将可能引发止损盘，导致进一步下行。反之，0.417692美元则是一个重要阻力位，突破该位有可能激发新的买盘，推动价格上涨。\n\n针对当前市场状况，建议投资者保持观望，待ADA价格突破关键的支撑和阻力位后再考虑入场。若短期内未能突破阻力位，建议谨慎操作，避免追高风险。"
    },
    "en": {
      "title": "Cardano vs US Dollar Technical Analysis",
      "content": "The recent price action of Cardano against the US Dollar (ADA/USD) shows a cautious upward trend, with the latest price at 0.415944, reflecting a modest 0.24% increase over the last 24 hours. The high and low for this period, at 0.417692 and 0.414323 respectively, indicate a range-bound environment. This consolidation phase suggests that traders are currently weighing the momentum and potential breakout points as they assess upcoming market conditions.\n\nFrom a technical perspective, the Simple Moving Average (SMA) at 20 periods sits at 0.41924525, which is slightly above the current price. This positioning indicates a potential resistance level that could hinder further upward movement unless breached convincingly. Investors should monitor this level closely, as a breakout above could signal a stronger bullish trend, while failure to rise could indicate a potential reversal or continued bearish pressure.\n\nThe MACD value of 0.0019370412 provides insight into the momentum behind the price action, though the lack of a signal line complicates the interpretation. This positive MACD reading suggests that there might be underlying bullish momentum, but without further confirmation, it’s essential to remain cautious. Traders should look for a more definitive signal in the coming sessions to confirm or negate this momentum.\n\nAs for support levels, the immediate support can be identified around the recent low of 0.414323. A drop below this level may lead to increased selling pressure, warranting a reevaluation of positions. Conversely, should the price maintain above this support and break through the 20-period SMA, traders might consider entering long positions with an initial target aligned with previous highs. Risk management strategies should be in place given the market's inherent volatility."
    }
  }
}