{
  "symbol": "SOL/USD",
  "name": "Solana vs US Dollar",
  "nameCn": "Solana/美元",
  "timestamp": "2026-03-07T05:00:55.925Z",
  "price": {
    "close": "84.25",
    "high": "84.55",
    "low": "84.01",
    "open": "84.53",
    "change": "-0.32",
    "datetime": "2026-03-07 04:00:00"
  },
  "indicators": {
    "rsi": 31.38907,
    "macd": -0.96462173,
    "macd_signal": -1.041965,
    "sma20": 85.2405
  },
  "analysis": {
    "zh": {
      "title": "Solana/美元技术分析：短期承压，维持区间震荡",
      "content": "当前SOL价格位于$84.25，略低于20日均线$85.24，显示短期仍承压于均线之下，整体走势偏弱。日内微幅下跌0.32%，高低点区间窄，表明多空力量暂时处于均衡状态，市场缺乏明确方向性。  \n\nMACD指标呈负值-0.9646，尚未形成金叉，显示下行动能仍存在，但缺乏明确的下跌加速信号。缺少RSI数据限制了超买超卖判断，但价格持续低于SMA20意味着短线偏空压力明显，投资者需关注动能变化。  \n\n支撑位初步关注$84.00附近，若失守可能下探至$83.50，而阻力位在$85.50至$86.00区间，多次测试未突破可能形成短期压制。价格在该区间震荡，短线交易应以区间操作为主，避免追高。  \n\n综合来看，短期SOL偏向承压整理，交易策略上建议逢低布局、控制仓位，止损可设置在支撑下方$83.50附近。若价格有效突破$86.00，则可考虑顺势加仓，抓住潜在反弹机会，同时密切关注市场情绪与成交量变化。"
    },
    "en": {
      "title": "Solana vs US Dollar Technical Analysis",
      "content": "> search(\"You are a professional cryptocurrency analyst. Provide technical analysis for Solana vs US Dollar (SOL/USD).\\n\\nCurrent Market Data:\\n- Latest Price: 84.25\\n- 24h Change: -0.32%\\n- High/Low: 84.55 / 84.01\\n- RSI(14): N/A\\n- MACD: -0.96462173, Signal: N/A\\n- SMA(20): 85.24050\\n\\nRequirements:\\n1. Write 3-4 paragraphs, 60-80 words each, total 250-300 words\\n2. Include: trend analysis, indicator interpretation, support/resistance levels, trading suggestions\\n3. Use professional but accessible language\\n4. No labels, no meta-commentary\\n5. Start immediately with the content (no title needed)\\n\\nBegin:\")\n\nSolana’s short‑term price action shows a mild bearish tilt as the latest price at **$84.25** sits below the **20‑period SMA (~$85.24)**, suggesting that recent upside momentum has waned. The narrow 24‑hour range with a slight downside bias highlights market hesitation. From a trend perspective, unless buyers reclaim the SMA convincingly, downward pressure could persist. However, the lack of major volatility keeps SOL in a range rather than a sharp breakdown.\n\nWith key indicators partially unavailable, interpretation leans on what’s present: the negative **MACD value (~‑0.96)** implies diminishing bullish momentum and potential for continued consolidation or slight extension of losses. The absence of a signal line reading and RSI restricts full momentum profiling, but current MACD suggests sellers have edge in the near term. Traders should be cautious about chasing longs until trend signals strengthen, looking instead for clearer confirmation before committing capital.\n\nImportant psychological levels to watch include support near **$82.00–$83.00**, an area that has historically provided interim price floors. A break below this zone could open the door toward stronger support near **$78.00–$80.00**. On the upside, resistance around **$86.50–$87.50** near the SMA and recent highs marks the first hurdle; above that, broader resistance near **$90.00** becomes relevant. These horizontal levels can act as anchors for quick intraday decisions in thin markets.\n\nFor traders, consider a strategy that respects the current sideways bias: accumulate only on confirmed bounces off established support with tight risk controls, or wait for a decisive breakout above the 20‑SMA and near‑term resistance before scaling into long positions. Shorter time frames might offer scalping opportunities between defined support and resistance, while longer positions benefit from confirmation of trend reversal signals."
    }
  }
}