{
  "symbol": "BTC/USD",
  "name": "Bitcoin vs US Dollar",
  "nameCn": "比特币/美元",
  "timestamp": "2026-02-16T19:21:27.160Z",
  "price": {
    "close": "67851.36",
    "high": "67955.95",
    "low": "67829.78",
    "open": "67829.78",
    "change": "0.03",
    "datetime": "2026-02-16 19:00:00"
  },
  "indicators": {
    "rsi": 41.085412,
    "macd": -308.067907,
    "macd_signal": -239.98583,
    "sma20": 68442.603
  },
  "analysis": {
    "zh": {
      "title": "比特币/美元技术分析：[震荡整理，短期走势缺乏明确方向]",
      "content": "当前比特币/美元（BTC/USD）市场呈现震荡整理的状态。价格在67829.78至67955.95之间波动，显示出短期内缺乏明确的趋势动力。虽然价格略有上涨，但变动幅度很小，市场情绪较为谨慎，缺乏强烈的买卖信号。\n\n从技术指标来看，RSI(14)尚未提供有效的超买或超卖信号，表明市场情绪仍处于中性状态。MACD指标的负值（-308.067907）显示出卖方仍占主导地位，但由于Signal线数据缺失，无法进一步确认趋势变化。此外，SMA(20)在68442.60附近，表明短期内有一定的阻力。\n\n支撑位方面，67829.78一线的低点可能提供短期支撑，若价格下破此水平，可能会迎来进一步的下行压力。阻力位在68000附近，突破此区域可能带来上涨动力，但当前缺乏足够的强势信号。\n\n建议短期内观望为主，避免追高或抄底，等待价格突破关键支撑或阻力位后再做决定。如果价格突破67829.78支撑，可以考虑适度减仓；若突破68000阻力，可能适合小规模进场。"
    },
    "en": {
      "title": "Bitcoin vs US Dollar Technical Analysis",
      "content": "Bitcoin's price has been trading within a narrow range recently, with a slight 0.03% change in the last 24 hours. The current price of $67,851.36 indicates a consolidation phase, where the market is unsure of its next move. The recent high of $67,955.95 and low of $67,829.78 suggest a small price range, highlighting a lack of volatility. In the absence of any significant trend shifts, the market is likely waiting for a catalyst to either drive prices higher or lead to a deeper correction.\n\nCurrently, the RSI (14) is unavailable, but based on the general price action, Bitcoin may be in a neutral zone. The MACD shows a negative value of -308.067907, indicating bearish momentum in the short term. However, since the signal line is not available, it’s essential to wait for confirmation before drawing any conclusions about potential trend reversals. For now, the market sentiment appears to be slightly pessimistic, though no major bearish trend has yet formed.\n\nFrom a technical perspective, the 20-period Simple Moving Average (SMA) at $68,442.60 provides an immediate resistance level. If Bitcoin fails to break above this resistance, there may be a potential for further consolidation or even a dip toward lower support levels. The SMA will act as a key indicator of the overall trend, with any significant moves above or below it indicating potential shifts in market sentiment. The price is currently hovering near support, and a break below $67,830 could signal further downside risk.\n\nFor traders, the market appears indecisive, which calls for caution. A breakout above $68,450 would open the possibility for a rally towards the next resistance at $69,000. Conversely, a break below $67,830 could trigger a deeper pullback, with support near $67,000. Given the current market conditions, a wait-and-see approach or a careful entry near support with a stop-loss strategy could be prudent until clearer signals emerge."
    }
  }
}