{
  "symbol": "ADA/USD",
  "name": "Cardano vs US Dollar",
  "nameCn": "艾达币/美元",
  "timestamp": "2026-04-07T13:14:42.141Z",
  "price": {
    "close": "0.243194",
    "high": "0.243689",
    "low": "0.242472",
    "open": "0.242472",
    "change": "0.25",
    "datetime": "2026-04-07 13:00:00"
  },
  "indicators": {
    "rsi": 34.42703,
    "macd": -0.0021745366,
    "macd_signal": -0.0019457129,
    "sma20": 0.2459281
  },
  "analysis": {
    "zh": {
      "title": "艾达币/美元技术分析：短期震荡偏弱",
      "content": "当前艾达币价格略高于日内低点但低于20日均线，显示短期多头动力不足，市场处于震荡整理阶段。价格在$0.2425$至$0.2440$区间内徘徊，短线波动有限，但整体偏向弱势整理。  \n\nMACD指标为负值，暗示下行压力存在，但尚未出现明确的死叉信号，短期空头潜力被一定支撑抑制。RSI数据缺失，但结合价格与均线关系，可推测市场买卖力量接近平衡，缺乏强烈趋势方向。  \n\n短期支撑位可关注$0.2425$，若跌破则可能触发进一步下行压力；阻力位在$0.2459$附近，即20日SMA位置，若突破该阻力，多头可能暂时获得反弹机会。交易者应关注价格对均线的反应，谨慎操作。  \n\n建议短线交易以震荡策略为主，低位尝试轻仓做多，高位可考虑部分获利或规避风险，避免追涨。中线投资者应等待价格稳步突破阻力或跌破支撑后，再布局更明确的趋势方向。"
    },
    "en": {
      "title": "Cardano vs US Dollar Technical Analysis",
      "content": "Cardano (ADA) has shown a largely sideways consolidation against the US Dollar in the latest trading session, hovering around $0.243. The narrow intraday range between $0.2425 and $0.2437 indicates low volatility and a lack of decisive momentum. Price action suggests that buyers and sellers are in relative equilibrium, with minor bullish pressure reflected in the slight positive change of 0.25% over 24 hours. Monitoring this range is crucial, as a breakout above or below it could set the tone for the next directional move.  \n\nThe short-term momentum appears slightly bearish relative to the 20-period simple moving average, currently at $0.2459. Trading below this SMA indicates mild resistance near the $0.246 level, where selling pressure could increase. MACD is negative at -0.00217, signaling subdued downward momentum, though the lack of a signal line prevents a full crossover analysis. RSI data is unavailable, but price’s proximity to the SMA suggests that the market is neither oversold nor overbought, supporting the idea of a consolidation phase.  \n\nKey support is located around $0.2425, which has held consistently in recent sessions and represents a short-term floor for buyers. On the upside, immediate resistance lies at $0.244 and extends to the SMA level at $0.2459. A decisive breach above these levels could trigger a moderate upward move toward $0.247–$0.248, while a break below $0.2425 may invite additional selling pressure toward $0.240. Traders should watch for volume confirmation on any breakout to avoid false signals in this tight range.  \n\nFrom a tactical perspective, short-term traders may consider range-bound strategies, buying near $0.2425 with a tight stop-loss, and targeting resistance levels around $0.244–$0.246. Conservative traders might wait for a confirmed break above the SMA or below the support to enter positions aligned with trend continuation. Overall, ADA/USD currently reflects market indecision, with potential for either a mild bullish bounce or a controlled pullback, making disciplined entry and exit planning essential."
    }
  }
}