{
  "symbol": "ADA/USD",
  "name": "Cardano vs US Dollar",
  "nameCn": "艾达币/美元",
  "timestamp": "2026-03-19T04:39:35.164Z",
  "price": {
    "close": "0.273022",
    "high": "0.274863",
    "low": "0.272445",
    "open": "0.274437",
    "change": "-0.60",
    "datetime": "2026-03-19 04:00:00"
  },
  "indicators": {
    "rsi": 37.78519,
    "macd": -0.003058709,
    "macd_signal": -0.0033910779,
    "sma20": 0.275224
  },
  "analysis": {
    "zh": {
      "title": "艾达币/美元技术分析：震荡整理，短期偏空",
      "content": "当前艾达币（ADA）/美元市场处于震荡整理的状态，价格在0.272445至0.274863之间波动，短期走势较为平淡。当前价格为0.273022，较24小时变化略有下跌，显示出市场的卖压略大。没有强烈的单边行情，价格可能继续在区间内波动。\n\nMACD指标显示为负值（-0.0031），表明短期内卖方占优，市场情绪偏向下行。尽管MACD信号线缺失，但这一负值表明短期内可能仍有一定的回调压力。由于RSI(14)缺失，我们无法从超买超卖的角度做进一步分析，但可以从MACD判断当前市场情绪。\n\n在支撑和阻力方面，0.272445是近期的支撑位，若跌破此价位，可能会进一步下探至0.2700附近。阻力位则位于0.275224附近，如果突破该价位，可能会测试0.2770的上行压力。因此，操作上建议短期内以区间震荡为主，谨慎操作，等待价格突破关键支撑或阻力位后再做决策。\n\n综合来看，短期内艾达币/美元价格偏向震荡整理，交易者可以关注支撑与阻力的突破情况。若价格跌破支撑位，空头可适当介入；若突破阻力位，则可考虑适量入场。"
    },
    "en": {
      "title": "Cardano vs US Dollar Technical Analysis",
      "content": "Cardano (ADA) is currently showing subtle bearish pressure as it trades around $0.2730, slightly below its 20-period simple moving average of $0.2752. The recent high of $0.2749 and low of $0.2724 suggest a narrow consolidation range, indicating indecision among short-term traders. The minor 24-hour decline of -0.60% aligns with this sideways pattern, hinting that momentum is weak but not strongly negative, which could favor short-term range-bound strategies until a decisive move occurs.  \n\nThe MACD value of -0.0031, without a confirmed signal line, reflects mild bearish sentiment. This suggests that the short-term momentum is slightly skewed downward, but the absence of a clear MACD crossover limits the reliability of trend confirmation. Traders should watch for the MACD line crossing above the signal for a potential bullish shift or further decline below zero for continued bearish pressure. The lack of RSI data prevents overbought/oversold assessment, emphasizing reliance on price action and moving averages.  \n\nKey support levels to monitor are around $0.2724, coinciding with the recent intraday low, and $0.2700, which aligns with a psychological round-number level. Resistance lies at the 20-period SMA near $0.2752 and extends to the $0.2775–$0.2780 range, where previous consolidation highs occurred. Breaking above these levels could open a short-term recovery opportunity, while failure to hold support might trigger deeper pullbacks. These levels provide a framework for cautious positioning.  \n\nFor trading considerations, short-term traders may focus on range plays, buying near support and trimming positions near resistance. More conservative participants could wait for a confirmed break above the SMA or MACD bullish crossover before committing to long positions. Risk management remains critical, especially given ADA’s current muted volatility and unclear directional momentum. Overall, the market leans mildly bearish but remains primed for potential short-term swings within a defined channel.  \n\nWord count: 268"
    }
  }
}