{
  "symbol": "XRP/USD",
  "name": "Ripple vs US Dollar",
  "nameCn": "瑞波币/美元",
  "timestamp": "2026-02-06T11:23:54.905Z",
  "price": {
    "close": "1.35565",
    "high": "1.36653",
    "low": "1.35153",
    "open": "1.35836",
    "change": "-0.23",
    "datetime": "2026-02-06 11:00:00"
  },
  "indicators": {
    "rsi": 56.053832,
    "macd": -0.010614783,
    "macd_signal": -0.031481269,
    "sma20": 1.2692
  },
  "analysis": {
    "zh": {
      "title": "瑞波币/美元技术分析：[震荡整理，关注关键支撑与阻力]",
      "content": "当前瑞波币/美元（XRP/USD）价格为1.35565，处于震荡整理的状态。24小时变化率较为平稳，仅为-0.23%。价格在1.35153至1.36653之间波动，显示出市场缺乏明确的方向性。投资者应关注价格能否突破这一区间，寻找趋势明确的信号。\n\n从技术指标来看，MACD目前显示负值（-0.0106），但没有明确的交叉信号，表明短期内的卖压相对较弱。SMA(20)为1.26920，价格较其上方略有支撑，暗示短期内可能维持相对稳定。RSI无法提供直接参考，但市场走势依然可以通过价格区间进行观察。\n\n支撑位方面，1.35153是当前较强的支撑区域，若跌破此位，可能会导致价格进一步回落。阻力位则位于1.36653附近，一旦突破这一水平，可能会开启新的上涨行情。因此，投资者可关注突破关键支撑或阻力位后的交易机会。\n\n综合来看，建议采取区间交易策略，等待价格接近支撑或阻力时进行操作。同时，建议保持灵活，密切关注MACD及其他技术指标的变化，及时调整策略。"
    },
    "en": {
      "title": "Ripple vs US Dollar Technical Analysis",
      "content": "The current market for XRP/USD presents a moderately bearish sentiment, as the price is showing a slight decline of 0.23% over the last 24 hours. The latest price of $1.35565 is near the lower end of its daily range, which has fluctuated between $1.36653 and $1.35153. This suggests that XRP is consolidating in the short term, and any break above the $1.366 level could signal a possible reversal towards a more neutral to bullish trend. However, the lack of a strong upward momentum leaves the market in a cautious posture.\n\nThe absence of an RSI (14) reading makes it difficult to gauge the strength of the current price movement. Nevertheless, the MACD reading of -0.0106 indicates that the market momentum is currently leaning bearish, though this is not yet a clear trend shift. The MACD histogram and the proximity of the current price to the SMA (20) of $1.26920 suggest that if the price continues to hold above the SMA, there is potential for a rebound, though the market has not yet confirmed any significant upward pressure.\n\nKey support lies at the recent low of $1.35153, which has held firm, while resistance is seen near $1.36653. If the price breaks through the $1.366 resistance, further upside could target $1.40, where the market could face additional selling pressure. On the other hand, a failure to hold above $1.35153 could open the door to lower levels, potentially targeting the $1.30 area, where buyers might step in to stabilize the price action.\n\nIn terms of trading suggestions, it would be wise to monitor the market for any clear breakout signals. A break above $1.366 may warrant a cautious long position, while a breach below $1.35153 could suggest the need for a short trade or avoidance of new long entries. Traders should also look for any MACD crossovers or RSI (14) updates for additional confirmation of trend shifts."
    }
  }
}