{
  "symbol": "SOL/USD",
  "name": "Solana vs US Dollar",
  "nameCn": "Solana/美元",
  "timestamp": "2026-01-01T03:21:09.058Z",
  "price": {
    "close": "125.08",
    "high": "125.11",
    "low": "124.86",
    "open": "124.97",
    "change": "0.10",
    "datetime": "2026-01-01 03:00:00"
  },
  "indicators": {
    "rsi": 51.77792,
    "macd": -0.080994749,
    "macd_signal": -0.060255231,
    "sma20": 125.151
  },
  "analysis": {
    "zh": {
      "title": "Solana/美元技术分析：[短期震荡趋势]",
      "content": "当前Solana（SOL/USD）价格为125.08，24小时内变化幅度较小，仅为0.10%。从技术走势来看，SOL在125.00附近形成了一定的支撑区域，反映出短期内市场情绪较为谨慎，整体趋势呈现出震荡整理的特征。\n\n在技术指标方面，MACD显示负值，表明当前市场动能偏弱，短期内可能难以突破125.11的高位。RSI虽然未提供，但结合当前价格走势，可能处于超买或中性区域，进一步确认市场缺乏强烈的买入信号。\n\n支撑位方面，125.00将是关键支撑，一旦跌破则可能导致进一步回调至124.86。阻力位则为125.11，若突破此位可望引发反弹行情，提升市场信心。因此，投资者需关注这些关键价位，以便做出及时的交易决策。\n\n综合来看，短期内SOL可能维持震荡整理的状态，建议投资者保持观望，耐心等待更明确的趋势信号。如果未来突破阻力位，可考虑适度介入，但在未突破前，谨慎操作，控制风险尤为重要。"
    },
    "en": {
      "title": "Solana vs US Dollar Technical Analysis",
      "content": "The current price of Solana against the US Dollar (SOL/USD) is at 125.08, reflecting a slight increase of 0.10% over the last 24 hours. This stability indicates a consolidative phase following recent volatility in the cryptocurrency market. The intraday high of 125.11 and low of 124.86 suggest a tight trading range, which may point toward indecision among traders. In the absence of a clear trend, price action will be crucial in determining the next significant move.\n\nTechnical indicators provide a mixed outlook on Solana's momentum. The RSI(14) is not available, making it challenging to assess overbought or oversold conditions. However, the MACD reading of -0.080994749 suggests that bearish momentum is present, albeit weak. The Simple Moving Average (SMA) of 20 days at 125.15 indicates a slight upward trend, which may provide support if the price approaches this level again. Traders should closely monitor these indicators for signs of potential reversals or continuations.\n\nSupport levels for SOL/USD can be identified around the recent low of 124.86, which may act as a critical barrier to downside movements. Should the price breach this level, the next support could be found around 124.50. Conversely, resistance is initially seen at 125.11, with a significant barrier at 126.00. A breakout above this level could attract bullish momentum, potentially leading to a retest of higher price ranges.\n\nFor traders, a cautious approach is advisable given the current market conditions. A buy opportunity could arise if SOL/USD breaks above 125.11 with strong volume, signaling a potential upward trend. Conversely, if the price falls below 124.86, a short position could be considered, targeting the next support level. It is essential to manage risk with appropriate stop-loss orders to safeguard against unexpected volatility in this dynamic market."
    }
  }
}